jawa/__init__.py
jawa/assemble.py
jawa/attribute.py
jawa/cf.py
jawa/classloader.py
jawa/cli.py
jawa/constants.py
jawa/fields.py
jawa/methods.py
jawa/transforms.py
jawa/attributes/__init__.py
jawa/attributes/bootstrap.py
jawa/attributes/code.py
jawa/attributes/constant_value.py
jawa/attributes/deprecated.py
jawa/attributes/enclosing_method.py
jawa/attributes/exceptions.py
jawa/attributes/inner_classes.py
jawa/attributes/line_number_table.py
jawa/attributes/local_variable.py
jawa/attributes/local_variable_type.py
jawa/attributes/signature.py
jawa/attributes/source_file.py
jawa/attributes/stack_map_table.py
jawa/attributes/synthetic.py
jawa/util/__init__.py
jawa/util/bytecode.json
jawa/util/bytecode.py
jawa/util/bytecode.yaml
jawa/util/descriptor.py
jawa/util/flags.py
jawa/util/shell.py
jawa/util/stream.py
jawa/util/tracer.py
jawa/util/utf.py
jawa/util/verifier.py
jawa-2.2.0.dist-info/LICENCE
jawa-2.2.0.dist-info/METADATA
jawa-2.2.0.dist-info/WHEEL
jawa-2.2.0.dist-info/entry_points.txt
jawa-2.2.0.dist-info/top_level.txt
jawa-2.2.0.dist-info/RECORD
