Metadata-Version: 2.1
Name: jawa
Version: 2.2.0
Summary: Doing fun stuff with JVM ClassFiles.
Home-page: http://github.com/TkTech/Jawa
Author: Tyler Kennedy
Author-email: tk@tkte.ch
License: UNKNOWN
Keywords: java,disassembly,disassembler,assembly
Platform: UNKNOWN
Classifier: Programming Language :: Python
Classifier: License :: OSI Approved :: MIT License
Classifier: Operating System :: OS Independent
Classifier: Development Status :: 3 - Alpha
Classifier: Intended Audience :: Developers
Classifier: Topic :: Software Development :: Disassemblers
Classifier: Topic :: Software Development :: Assemblers
Requires-Python: >=3.6
Provides-Extra: dev
